signwriting/__init__.py
signwriting/server.py
signwriting/types.py
signwriting/fingerspelling/__init__.py
signwriting/fingerspelling/fingerspelling.py
signwriting/fingerspelling/server.py
signwriting/fingerspelling/test_fingerspelling.py
signwriting/fingerspelling/visualize_fingerspelling.py
signwriting/fingerspelling/data/da-dk-dsl-dts.txt
signwriting/fingerspelling/data/de-ch-sgg-dsgs.txt
signwriting/fingerspelling/data/de-de-gsg-dgs.txt
signwriting/fingerspelling/data/en-gb-bfi-bsl.txt
signwriting/fingerspelling/data/en-ie-isg-isl.txt
signwriting/fingerspelling/data/en-us-ase-asl.txt
signwriting/fingerspelling/data/es-es-ssp-lse.txt
signwriting/fingerspelling/data/es-hn-hds-lesho.txt
signwriting/fingerspelling/data/es-mx-mfs-lsm.txt
signwriting/fingerspelling/data/es-ni-ncs-isn.txt
signwriting/fingerspelling/data/fr-be-sfb-lsfb.txt
signwriting/fingerspelling/data/fr-fr-fsl-lsf.txt
signwriting/fingerspelling/data/he-il-isr-isl.txt
signwriting/fingerspelling/data/it-it-ise-lis.txt
signwriting/fingerspelling/data/ja-jp-jsl-jsl.txt
signwriting/fingerspelling/data/ko-kr-ko-ksl.txt
signwriting/fingerspelling/data/nl-be-vgt-vgt.txt
signwriting/fingerspelling/data/no-no-nsl-nsl.txt
signwriting/fingerspelling/data/pt-br-bzs-libras.txt
signwriting/fingerspelling/data/pt-pt-psr-lsp.txt
signwriting/fingerspelling/data/sv-se-swl-ssl.txt
signwriting/fingerspelling/data/th-th-tsq-thsl.txt
signwriting/fingerspelling/data/zh-cn-csl-csl.txt
signwriting/formats/__init__.py
signwriting/formats/fsw_to_sign.py
signwriting/formats/fsw_to_swu.py
signwriting/formats/sign_to_fsw.py
signwriting/formats/swu.py
signwriting/formats/swu_to_fsw.py
signwriting/formats/test_fsw_to_sign.py
signwriting/formats/test_swu.py
signwriting/formats/test_swu_to_fsw.py
signwriting/hamnosys/parallel.json
signwriting/mouthing/__init__.py
signwriting/mouthing/mouthing.json
signwriting/mouthing/mouthing.py
signwriting/mouthing/server.py
signwriting/mouthing/visualize_mouthing.py
signwriting-0.1.1.dist-info/licenses/LICENSE
signwriting-0.1.1.dist-info/METADATA
signwriting-0.1.1.dist-info/WHEEL
signwriting-0.1.1.dist-info/top_level.txt
signwriting-0.1.1.dist-info/RECORD
