Metadata-Version: 2.4
Name: signwriting
Version: 0.1.1
Summary: Python utilities for SignWriting.
Author-email: Amit Moryossef <amitmoryossef@gmail.com>
License-File: LICENSE
Requires-Dist: Pillow
Provides-Extra: dev
Requires-Dist: pytest; extra == "dev"
Requires-Dist: pylint; extra == "dev"
Requires-Dist: numpy; extra == "dev"
Provides-Extra: mouthing
Requires-Dist: epitran; extra == "mouthing"
Requires-Dist: g2pk; extra == "mouthing"
Provides-Extra: server
Requires-Dist: Flask; extra == "server"
Requires-Dist: Flask-RESTful; extra == "server"
Requires-Dist: Flask-Cors; extra == "server"
Requires-Dist: gunicorn; extra == "server"
Dynamic: license-file
